[
    {
        "name": "MEU ESPAÇO",
        "path": "mySpaceHome.png",
        "size": "10",
        "margin": "8",
        "color": "#DDA1FA",
        "redirect": "myspace"
    },
    {
        "name": "HORA DA HISTÓRIA",
        "path": "storyTimeHome.png",
        "size": "20",
        "margin": "5",
        "color": "#9CEF79",
        "redirect": "story"
    },
    {
        "name": "CALENDÁRIO",
        "path": "calendarHome.png",
        "size": "13",
        "margin": "14",
        "color": "#FECC33",
        "redirect": "calendar"
    }
]